{
    "nodes": [
        {
            "node": "MS_Memcached.1",
            "label": "Memcached"
        },
        {
            "node": "MS_normal+3.3",
            "label": "normal"
        },
        {
            "node": "MS_normal+3.20",
            "label": "normal"
        },
        {
            "node": "MS_normal+5.2",
            "label": "normal"
        },
        {
            "node": "MS_normal+3.4",
            "label": "normal"
        },
        {
            "node": "MS_normal+3.3",
            "label": "normal"
        },
        {
            "node": "MS_normal+3.4",
            "label": "normal"
        },
        {
            "node": "MS_normal+3.17",
            "label": "normal"
        },
        {
            "node": "MS_normal+3.3",
            "label": "normal"
        },
        {
            "node": "MS_relay+5.1_func7",
            "label": "relay"
        },
        {
            "node": "MS_normal+3.5",
            "label": "normal"
        },
        {
            "node": "MS_normal+3.5_func1",
            "label": "normal"
        },
        {
            "node": "MS_normal+4.20",
            "label": "normal"
        },
        {
            "node": "MS_normal+3.9",
            "label": "normal"
        },
        {
            "node": "MS_normal+2.3",
            "label": "normal"
        },
        {
            "node": "USER",
            "label": "relay"
        }
    ],
    "edges": [
        {
            "source": "MS_Memcached.1",
            "target": "MS_Memcached.1",
            "weight": 2,
            "rpctype": "mc"
        },
        {
            "source": "MS_normal+3.3",
            "target": "MS_normal+3.9",
            "weight": 1,
            "rpctype": "http"
        },
        {
            "source": "MS_normal+3.20",
            "target": "MS_normal+5.2",
            "weight": 1,
            "rpctype": "http"
        },
        {
            "source": "MS_normal+5.2",
            "target": "MS_normal+3.3",
            "weight": 1,
            "rpctype": "http"
        },
        {
            "source": "MS_normal+3.4",
            "target": "MS_normal+3.17",
            "weight": 2,
            "rpctype": "http"
        },
        {
            "source": "MS_normal+3.3",
            "target": "MS_normal+3.4",
            "weight": 1,
            "rpctype": "http"
        },
        {
            "source": "MS_normal+3.3",
            "target": "MS_normal+3.3",
            "weight": 1,
            "rpctype": "http"
        },
        {
            "source": "MS_normal+3.3",
            "target": "MS_normal+3.3",
            "weight": 1,
            "rpctype": "http"
        },
        {
            "source": "MS_normal+3.4",
            "target": "MS_normal+3.5",
            "weight": 1,
            "rpctype": "http"
        },
        {
            "source": "MS_normal+3.17",
            "target": "MS_normal+3.20",
            "weight": 1,
            "rpctype": "http"
        },
        {
            "source": "MS_relay+5.1_func7",
            "target": "MS_Memcached.1",
            "weight": 2,
            "rpctype": "mc"
        },
        {
            "source": "MS_normal+3.5",
            "target": "MS_normal+4.20",
            "weight": 1,
            "rpctype": "http"
        },
        {
            "source": "MS_normal+3.5_func1",
            "target": "MS_relay+5.1_func7",
            "weight": 1,
            "rpctype": "rpc"
        },
        {
            "source": "MS_normal+4.20",
            "target": "MS_normal+3.5_func1",
            "weight": 2,
            "rpctype": "rpc"
        },
        {
            "source": "MS_normal+3.9",
            "target": "MS_normal+3.4",
            "weight": 1,
            "rpctype": "http"
        },
        {
            "source": "MS_normal+2.3",
            "target": "MS_normal+3.3",
            "weight": 1,
            "rpctype": "http"
        },
        {
            "source": "USER",
            "target": "MS_normal+2.3",
            "weight": 1,
            "rpctype": "http"
        }
    ],
    "num": 1
}