{
    "nodes": [
        {
            "node": "MS_normal+2.1",
            "label": "normal"
        },
        {
            "node": "MS_blackhole.2_func503",
            "label": "blackhole"
        },
        {
            "node": "MS_blackhole.2_func504",
            "label": "blackhole"
        },
        {
            "node": "MS_normal+3.1_func497",
            "label": "normal"
        },
        {
            "node": "MS_normal+3.1_func498",
            "label": "normal"
        },
        {
            "node": "MS_normal+3.1_func499",
            "label": "normal"
        },
        {
            "node": "MS_normal+3.1_func500",
            "label": "normal"
        },
        {
            "node": "MS_normal+3.1_func501",
            "label": "normal"
        },
        {
            "node": "MS_normal+3.1_func502",
            "label": "normal"
        },
        {
            "node": "MS_normal+3.1_func505",
            "label": "normal"
        },
        {
            "node": "MS_normal+3.1_func506",
            "label": "normal"
        },
        {
            "node": "MS_normal+3.1_func507",
            "label": "normal"
        },
        {
            "node": "MS_normal+3.1_func508",
            "label": "normal"
        },
        {
            "node": "MS_normal+3.1_func509",
            "label": "normal"
        },
        {
            "node": "MS_normal+3.1_func510",
            "label": "normal"
        },
        {
            "node": "MS_normal+3.1_func511",
            "label": "normal"
        },
        {
            "node": "MS_normal+3.1_func512",
            "label": "normal"
        },
        {
            "node": "USER",
            "label": "relay"
        }
    ],
    "edges": [
        {
            "source": "MS_normal+2.1",
            "target": "MS_blackhole.2_func503",
            "weight": 1,
            "rpctype": "rpc"
        },
        {
            "source": "MS_normal+2.1",
            "target": "MS_blackhole.2_func504",
            "weight": 1,
            "rpctype": "rpc"
        },
        {
            "source": "MS_normal+2.1",
            "target": "MS_normal+3.1_func497",
            "weight": 1,
            "rpctype": "rpc"
        },
        {
            "source": "MS_normal+2.1",
            "target": "MS_normal+3.1_func498",
            "weight": 1,
            "rpctype": "rpc"
        },
        {
            "source": "MS_normal+2.1",
            "target": "MS_normal+3.1_func499",
            "weight": 1,
            "rpctype": "rpc"
        },
        {
            "source": "MS_normal+2.1",
            "target": "MS_normal+3.1_func500",
            "weight": 1,
            "rpctype": "rpc"
        },
        {
            "source": "MS_normal+2.1",
            "target": "MS_normal+3.1_func501",
            "weight": 1,
            "rpctype": "rpc"
        },
        {
            "source": "MS_normal+2.1",
            "target": "MS_normal+3.1_func502",
            "weight": 1,
            "rpctype": "rpc"
        },
        {
            "source": "MS_normal+2.1",
            "target": "MS_normal+3.1_func505",
            "weight": 1,
            "rpctype": "rpc"
        },
        {
            "source": "MS_normal+2.1",
            "target": "MS_normal+3.1_func506",
            "weight": 1,
            "rpctype": "rpc"
        },
        {
            "source": "MS_normal+2.1",
            "target": "MS_normal+3.1_func507",
            "weight": 1,
            "rpctype": "rpc"
        },
        {
            "source": "MS_normal+2.1",
            "target": "MS_normal+3.1_func508",
            "weight": 1,
            "rpctype": "rpc"
        },
        {
            "source": "MS_normal+2.1",
            "target": "MS_normal+3.1_func509",
            "weight": 1,
            "rpctype": "rpc"
        },
        {
            "source": "MS_normal+2.1",
            "target": "MS_normal+3.1_func510",
            "weight": 1,
            "rpctype": "rpc"
        },
        {
            "source": "MS_normal+2.1",
            "target": "MS_normal+3.1_func511",
            "weight": 1,
            "rpctype": "rpc"
        },
        {
            "source": "MS_normal+2.1",
            "target": "MS_normal+3.1_func512",
            "weight": 1,
            "rpctype": "rpc"
        },
        {
            "source": "USER",
            "target": "MS_normal+2.1",
            "weight": 1,
            "rpctype": "http"
        }
    ],
    "num": 24
}