{
    "nodes": [
        {
            "node": "MS_relay+2.1",
            "label": "relay"
        },
        {
            "node": "MS_normal+3.1_func366",
            "label": "normal"
        },
        {
            "node": "MS_normal+3.1_func173",
            "label": "normal"
        },
        {
            "node": "MS_normal+3.1_func21",
            "label": "normal"
        },
        {
            "node": "MS_normal+3.1_func364",
            "label": "normal"
        },
        {
            "node": "MS_normal+3.1_func197",
            "label": "normal"
        },
        {
            "node": "MS_normal+3.1_func24",
            "label": "normal"
        },
        {
            "node": "MS_normal+3.1_func12",
            "label": "normal"
        },
        {
            "node": "MS_normal+3.1_func362",
            "label": "normal"
        },
        {
            "node": "MS_normal+3.1_func515",
            "label": "normal"
        },
        {
            "node": "USER",
            "label": "relay"
        }
    ],
    "edges": [
        {
            "source": "MS_relay+2.1",
            "target": "MS_normal+3.1_func366",
            "weight": 1,
            "rpctype": "rpc"
        },
        {
            "source": "MS_relay+2.1",
            "target": "MS_normal+3.1_func173",
            "weight": 5,
            "rpctype": "rpc"
        },
        {
            "source": "MS_relay+2.1",
            "target": "MS_normal+3.1_func21",
            "weight": 1,
            "rpctype": "rpc"
        },
        {
            "source": "MS_relay+2.1",
            "target": "MS_normal+3.1_func364",
            "weight": 1,
            "rpctype": "rpc"
        },
        {
            "source": "MS_relay+2.1",
            "target": "MS_normal+3.1_func24",
            "weight": 1,
            "rpctype": "rpc"
        },
        {
            "source": "MS_relay+2.1",
            "target": "MS_normal+3.1_func362",
            "weight": 1,
            "rpctype": "rpc"
        },
        {
            "source": "MS_relay+2.1",
            "target": "MS_normal+3.1_func515",
            "weight": 1,
            "rpctype": "rpc"
        },
        {
            "source": "MS_normal+3.1_func366",
            "target": "MS_normal+3.1_func12",
            "weight": 1,
            "rpctype": "rpc"
        },
        {
            "source": "MS_normal+3.1_func362",
            "target": "MS_normal+3.1_func197",
            "weight": 1,
            "rpctype": "rpc"
        },
        {
            "source": "USER",
            "target": "MS_relay+2.1",
            "weight": 1,
            "rpctype": "http"
        }
    ],
    "num": 3
}