{
    "nodes": [
        {
            "node": "MS_normal+3.1_func489",
            "label": "normal"
        },
        {
            "node": "MS_normal+3.1_func2",
            "label": "normal"
        },
        {
            "node": "MS_normal+3.1_func60",
            "label": "normal"
        },
        {
            "node": "MS_normal+3.1_func58",
            "label": "normal"
        },
        {
            "node": "MS_normal+3.1_func1",
            "label": "normal"
        },
        {
            "node": "MS_normal+3.1_func17",
            "label": "normal"
        },
        {
            "node": "MS_relay+2.1",
            "label": "relay"
        },
        {
            "node": "USER",
            "label": "relay"
        }
    ],
    "edges": [
        {
            "source": "MS_normal+3.1_func60",
            "target": "MS_normal+3.1_func2",
            "weight": 1,
            "rpctype": "rpc"
        },
        {
            "source": "MS_relay+2.1",
            "target": "MS_normal+3.1_func489",
            "weight": 1,
            "rpctype": "rpc"
        },
        {
            "source": "MS_relay+2.1",
            "target": "MS_normal+3.1_func60",
            "weight": 1,
            "rpctype": "rpc"
        },
        {
            "source": "MS_relay+2.1",
            "target": "MS_normal+3.1_func58",
            "weight": 1,
            "rpctype": "rpc"
        },
        {
            "source": "MS_relay+2.1",
            "target": "MS_normal+3.1_func1",
            "weight": 1,
            "rpctype": "rpc"
        },
        {
            "source": "MS_relay+2.1",
            "target": "MS_normal+3.1_func17",
            "weight": 5,
            "rpctype": "rpc"
        },
        {
            "source": "USER",
            "target": "MS_relay+2.1",
            "weight": 1,
            "rpctype": "http"
        }
    ],
    "num": 1
}