{
    "nodes": [
        {
            "node": "MS_normal+3.1_func1034",
            "label": "normal"
        },
        {
            "node": "MS_normal+3.1_func680",
            "label": "normal"
        },
        {
            "node": "MS_normal+3.1_func686",
            "label": "normal"
        },
        {
            "node": "MS_normal+3.1_func221",
            "label": "normal"
        },
        {
            "node": "MS_normal+3.1_func4",
            "label": "normal"
        },
        {
            "node": "MS_normal+3.1_func5",
            "label": "normal"
        },
        {
            "node": "MS_normal+3.1_func9",
            "label": "normal"
        },
        {
            "node": "MS_normal+3.1_func641",
            "label": "normal"
        },
        {
            "node": "MS_blackhole.1_func7",
            "label": "blackhole"
        },
        {
            "node": "MS_relay+2.1",
            "label": "relay"
        },
        {
            "node": "USER",
            "label": "relay"
        }
    ],
    "edges": [
        {
            "source": "MS_normal+3.1_func680",
            "target": "MS_normal+3.1_func5",
            "weight": 1,
            "rpctype": "rpc"
        },
        {
            "source": "MS_normal+3.1_func641",
            "target": "MS_normal+3.1_func4",
            "weight": 1,
            "rpctype": "rpc"
        },
        {
            "source": "MS_relay+2.1",
            "target": "MS_normal+3.1_func1034",
            "weight": 1,
            "rpctype": "rpc"
        },
        {
            "source": "MS_relay+2.1",
            "target": "MS_normal+3.1_func680",
            "weight": 1,
            "rpctype": "rpc"
        },
        {
            "source": "MS_relay+2.1",
            "target": "MS_normal+3.1_func686",
            "weight": 1,
            "rpctype": "rpc"
        },
        {
            "source": "MS_relay+2.1",
            "target": "MS_normal+3.1_func221",
            "weight": 5,
            "rpctype": "rpc"
        },
        {
            "source": "MS_relay+2.1",
            "target": "MS_normal+3.1_func9",
            "weight": 1,
            "rpctype": "rpc"
        },
        {
            "source": "MS_relay+2.1",
            "target": "MS_normal+3.1_func641",
            "weight": 1,
            "rpctype": "rpc"
        },
        {
            "source": "MS_relay+2.1",
            "target": "MS_blackhole.1_func7",
            "weight": 1,
            "rpctype": "rpc"
        },
        {
            "source": "USER",
            "target": "MS_relay+2.1",
            "weight": 1,
            "rpctype": "http"
        }
    ],
    "num": 1
}