{
    "nodes": [
        {
            "node": "MS_relay+2.1",
            "label": "relay"
        },
        {
            "node": "MS_normal+3.1_func357",
            "label": "normal"
        },
        {
            "node": "MS_normal+3.1_func151",
            "label": "normal"
        },
        {
            "node": "MS_normal+3.1_func21",
            "label": "normal"
        },
        {
            "node": "MS_normal+3.1_func349",
            "label": "normal"
        },
        {
            "node": "MS_normal+3.1_func864",
            "label": "normal"
        },
        {
            "node": "MS_normal+3.1_func197",
            "label": "normal"
        },
        {
            "node": "MS_normal+3.1_func24",
            "label": "normal"
        },
        {
            "node": "MS_normal+3.1_func12",
            "label": "normal"
        },
        {
            "node": "MS_normal+3.1_func562",
            "label": "normal"
        },
        {
            "node": "USER",
            "label": "relay"
        }
    ],
    "edges": [
        {
            "source": "MS_relay+2.1",
            "target": "MS_normal+3.1_func357",
            "weight": 1,
            "rpctype": "rpc"
        },
        {
            "source": "MS_relay+2.1",
            "target": "MS_normal+3.1_func151",
            "weight": 5,
            "rpctype": "rpc"
        },
        {
            "source": "MS_relay+2.1",
            "target": "MS_normal+3.1_func21",
            "weight": 1,
            "rpctype": "rpc"
        },
        {
            "source": "MS_relay+2.1",
            "target": "MS_normal+3.1_func349",
            "weight": 1,
            "rpctype": "rpc"
        },
        {
            "source": "MS_relay+2.1",
            "target": "MS_normal+3.1_func864",
            "weight": 1,
            "rpctype": "rpc"
        },
        {
            "source": "MS_relay+2.1",
            "target": "MS_normal+3.1_func24",
            "weight": 1,
            "rpctype": "rpc"
        },
        {
            "source": "MS_relay+2.1",
            "target": "MS_normal+3.1_func562",
            "weight": 1,
            "rpctype": "rpc"
        },
        {
            "source": "MS_normal+3.1_func349",
            "target": "MS_normal+3.1_func197",
            "weight": 1,
            "rpctype": "rpc"
        },
        {
            "source": "MS_normal+3.1_func864",
            "target": "MS_normal+3.1_func12",
            "weight": 1,
            "rpctype": "rpc"
        },
        {
            "source": "USER",
            "target": "MS_relay+2.1",
            "weight": 1,
            "rpctype": "http"
        }
    ],
    "num": 1
}